gitformsaver/__init__.py
gitformsaver/authentication.py
gitformsaver/authentication_interface.py
gitformsaver/authentication_service.py
gitformsaver/cli.py
gitformsaver/errors.py
gitformsaver/form_saver_service.py
gitformsaver/formatters.py
gitformsaver/formatters_loader.py
gitformsaver/git_client.py
gitformsaver/git_ops.py
gitformsaver/git_task_handler.py
gitformsaver/git_thread.py
gitformsaver/git_thread_manager.py
gitformsaver/git_url_parse.py
gitformsaver/http_server.py
gitformsaver/json_formatter.py
gitformsaver/lazy_git.py
gitformsaver/plain_text_formatter.py
gitformsaver/security.py
git_form_saver-0.0.4.dist-info/LICENSE
git_form_saver-0.0.4.dist-info/METADATA
git_form_saver-0.0.4.dist-info/WHEEL
git_form_saver-0.0.4.dist-info/entry_points.txt
git_form_saver-0.0.4.dist-info/top_level.txt
git_form_saver-0.0.4.dist-info/RECORD
