Metadata-Version: 2.1
Name: git-form-saver
Version: 0.0.4
Summary: Git form saver
Home-page: https://github.com/peterdemin/git-form-saver
Author: Peter Demin
Author-email: peterdemin@gmail.com
License: MIT license
Keywords: git http form saver
Classifier: Development Status :: 4 - Beta
Classifier: Intended Audience :: Developers
Classifier: License :: OSI Approved :: MIT License
Classifier: Natural Language :: English
Classifier: Programming Language :: Python :: 3.10
Requires-Python: >=3.10
License-File: LICENSE
Requires-Dist: aiohttp
Requires-Dist: aiohttp-jinja2
Requires-Dist: GitPython
Requires-Dist: marshmallow
Requires-Dist: cryptography
Requires-Dist: pyjwt[crypto]
